convert_yaml.py
setup.py
appengine_config_transformer.egg-info/PKG-INFO
appengine_config_transformer.egg-info/SOURCES.txt
appengine_config_transformer.egg-info/dependency_links.txt
appengine_config_transformer.egg-info/entry_points.txt
appengine_config_transformer.egg-info/top_level.txt
yaml_conversion/__init__.py
yaml_conversion/converters.py
yaml_conversion/schema.py
yaml_conversion/yaml_schema.py
yaml_conversion/lib/__init__.py
yaml_conversion/lib/google/__init__.py
yaml_conversion/lib/google/appengine/__init__.py
yaml_conversion/lib/google/appengine/api/__init__.py
yaml_conversion/lib/google/appengine/api/appinfo.py
yaml_conversion/lib/google/appengine/api/appinfo_errors.py
yaml_conversion/lib/google/appengine/api/backendinfo.py
yaml_conversion/lib/google/appengine/api/pagespeedinfo.py
yaml_conversion/lib/google/appengine/api/validation.py
yaml_conversion/lib/google/appengine/api/yaml_builder.py
yaml_conversion/lib/google/appengine/api/yaml_errors.py
yaml_conversion/lib/google/appengine/api/yaml_listener.py
yaml_conversion/lib/google/appengine/api/yaml_object.py