Metadata-Version: 1.0
Name: appengine-config-transformer
Version: 0.1
Summary: Tool for converting between YAML and JSON representations.
Home-page: UNKNOWN
Author: UNKNOWN
Author-email: UNKNOWN
License: UNKNOWN
Platform: UNKNOWN
